[{"id":1231123,"title":"С‹С‹С‹","content":"С‡РµР±СѓРїРµРє","createdAt":"2026-03-30T20:59:48.865079","isFavorite":false,"tags":["niga"]},{"id":123,"title":"HASDUFHWeufh;ihРѕС†С‹СѓСЂР°С€РіС‰С†СѓСЂР°Р№С†С‹СЂРІР°Р·Р№С†СЂРІРћР›Р Р¤РЈР«РЁР“РђР Р™Р¤Р¦Р–РЁР©Р“Р Рђ","content":"Р№С†СѓРѕС€Р°СЂС†Р·РіС€СѓР°СЂС†РіС€СѓСЂРї","createdAt":"2026-03-30T21:01:16.400638","isFavorite":false,"tags":["1"]},{"id":123,"title":"РЅР° СЂСѓСЃСЃРєРѕРјРё","content":"С…РѕС‡Сѓ Р·Р°РјРµС‚РєРѕ","createdAt":"2026-03-30T21:03:37.133842","isFavorite":false,"tags":["РЅРµРё"]},{"id":123145115,"title":"РІРѕРЅСЋС‡РёРµ СЏР№С†С‹ ","content":"С‹С‹С‹С‹С‹","createdAt":"2026-03-30T21:08:20.690681","isFavorite":false,"tags":["РЅРµС‚"]},{"id":12331,"title":"ghghg","content":"\u0000\u0000\u0000\u0000\u0000\u0000\u0000\u0000\u0000\u0000","createdAt":"2026-03-31T14:54:35.819800","isFavorite":false,"tags":["\u0000\u0000\u0000\u0000\u0000\u0000"]}]